{
    "Ar36": {
        "error": 0.0001865355263672427,
        "error_type": "SEM",
        "filter_outliers_dict": {
            "filter_outliers": true,
            "iterations": 1,
            "std_devs": 3,
            "use_iqr_filtering": false,
            "use_standard_deviation_filtering": false
        },
        "fit": "parabolic",
        "fn": 279,
        "include_baseline_error": true,
        "n": 280,
        "outlier_excluded": [
            224
        ],
        "reviewed": true,
        "user_excluded": [],
        "value": 0.0020298219737842566
    },
    "Ar37": {
        "error": 0.003749201623189493,
        "error_type": "SEM",
        "filter_outliers_dict": {
            "filter_outliers": true,
            "iterations": 1,
            "std_devs": 3,
            "use_iqr_filtering": false,
            "use_standard_deviation_filtering": false
        },
        "fit": "linear",
        "fn": 280,
        "include_baseline_error": true,
        "n": 280,
        "outlier_excluded": [],
        "reviewed": true,
        "user_excluded": [],
        "value": -0.02989300764184788
    },
    "Ar38": {
        "error": 0.003196748760732556,
        "error_type": "SEM",
        "filter_outliers_dict": {
            "filter_outliers": true,
            "iterations": 1,
            "std_devs": 3,
            "use_iqr_filtering": false,
            "use_standard_deviation_filtering": false
        },
        "fit": "linear",
        "fn": 278,
        "include_baseline_error": true,
        "n": 280,
        "outlier_excluded": [
            192,
            222
        ],
        "reviewed": true,
        "user_excluded": [],
        "value": 0.0252743696553768
    },
    "Ar39": {
        "error": 0.013385187144172596,
        "error_type": "SEM",
        "filter_outliers_dict": {
            "filter_outliers": true,
            "iterations": 1,
            "std_devs": 3,
            "use_iqr_filtering": false,
            "use_standard_deviation_filtering": false
        },
        "fit": "parabolic",
        "fn": 279,
        "include_baseline_error": true,
        "n": 280,
        "outlier_excluded": [
            198
        ],
        "reviewed": true,
        "user_excluded": [],
        "value": 0.05887396413392193
    },
    "Ar40": {
        "error": 0.010217240685742738,
        "error_type": "SEM",
        "filter_outliers_dict": {
            "filter_outliers": true,
            "iterations": 1,
            "std_devs": 3,
            "use_iqr_filtering": false,
            "use_standard_deviation_filtering": false
        },
        "fit": "parabolic",
        "fn": 279,
        "include_baseline_error": true,
        "n": 280,
        "outlier_excluded": [
            78
        ],
        "reviewed": true,
        "user_excluded": [],
        "value": 0.1548855794541844
    },
    "Ar41": {
        "error": 0.032656827078735795,
        "error_type": "SEM",
        "filter_outliers_dict": {
            "filter_outliers": true,
            "iterations": 1,
            "std_devs": 2
        },
        "fit": "linear",
        "value": -0.3315236772935247
    }
}